VestaService/Document.py
VestaService/DownloadRemote.py
VestaService/Message.py
VestaService/RemoteAccess.py
VestaService/Report.py
VestaService/__init__.py
VestaService/__meta__.py
VestaService/annotations_dispatcher.py
VestaService/request.py
VestaService/request_process_mesg.py
VestaService/sentry_agent.py
VestaService/service_exceptions.py
VestaService/stub.py
VestaService-0.4.3.dist-info/LICENSE
VestaService-0.4.3.dist-info/METADATA
VestaService-0.4.3.dist-info/WHEEL
VestaService-0.4.3.dist-info/entry_points.txt
VestaService-0.4.3.dist-info/top_level.txt
VestaService-0.4.3.dist-info/RECORD
