Metadata-Version: 2.1
Name: VestaService
Version: 0.4.3
Summary: Code to facilitate creation of services and their integration to Vesta Service Gateway.
Home-page: https://github.com/crim-ca/Service
Author: Frederic Osterrath
Author-email: osterrfr@crim.ca
License: Apache 2.0
Keywords: Vesta,Service
Platform: linux_x86_64
Classifier: Development Status :: 4 - Beta
Classifier: Intended Audience :: Developers
Classifier: Topic :: Software Development :: Libraries :: Application Frameworks
Classifier: License :: OSI Approved :: Apache Software License
Classifier: Natural Language :: English
Classifier: Programming Language :: Python :: 2
Classifier: Programming Language :: Python :: 2.7
Classifier: Programming Language :: Python :: 3
Classifier: Programming Language :: Python :: 3.4
Classifier: Programming Language :: Python :: 3.5
Requires-Dist: celery (==4.3.0)
Requires-Dist: requests[security] (>=2.20.0)
Requires-Dist: sentry-sdk
